[
  {
    "id": "mercor-1",
    "job_title": "Generalist Expert",
    "company_name": "Mercor",
    "location": "Remote",
    "job_type": "Hourly Contract",
    "salary_range": "$60 – $200/hr",
    "monthly_earnings": "$9,600+/mo",
    "required_skills": ["Analytical Skills", "Writing", "English Fluency", "Research"],
    "match_score": 94,
    "skill_overlap": ["Analytical Skills", "Writing", "Research"],
    "missing_skills": [],
    "hired_count": 38,
    "job_link": "https://t.mercor.com/GCMIs",
    "is_featured": true,
    "pay_label": "$60–$200/hour"
  },
  {
    "id": "mercor-2",
    "job_title": "Professional Design Expert",
    "company_name": "Mercor",
    "location": "Remote",
    "job_type": "Hourly Contract",
    "salary_range": "$80 – $180/hr",
    "monthly_earnings": "$12,800+/mo",
    "required_skills": ["UI Design", "Graphic Design", "Figma", "Branding"],
    "match_score": 88,
    "skill_overlap": ["UI Design", "Figma"],
    "missing_skills": ["Branding"],
    "hired_count": 22,
    "job_link": "https://t.mercor.com/u4L6a",
    "is_featured": true,
    "pay_label": "$80–$180/hour"
  },
  {
    "id": "mercor-3",
    "job_title": "Financial Analyst",
    "company_name": "Mercor",
    "location": "Remote",
    "job_type": "Hourly Contract",
    "salary_range": "$80 – $160/hr",
    "monthly_earnings": "$11,200+/mo",
    "required_skills": ["Excel", "PowerPoint", "Financial Analysis", "Business Analysis", "Word"],
    "match_score": 91,
    "skill_overlap": ["Excel", "Financial Analysis"],
    "missing_skills": ["Business Analysis"],
    "hired_count": 17,
    "job_link": "https://t.mercor.com/u4L6a",
    "is_featured": true,
    "pay_label": "$80–$160/hour"
  },
  {
    "id": "mercor-4",
    "job_title": "Artifact Expert — Word Specialist",
    "company_name": "Mercor",
    "location": "Remote",
    "job_type": "Hourly Contract",
    "salary_range": "$60 – $90/hr",
    "monthly_earnings": "$6,400+/mo",
    "required_skills": ["Microsoft Word", "Document Formatting", "Templates", "Sections", "References"],
    "match_score": 85,
    "skill_overlap": ["Microsoft Word", "Document Formatting"],
    "missing_skills": ["Templates"],
    "hired_count": 11,
    "job_link": "https://t.mercor.com/rOcNv",
    "is_featured": true,
    "pay_label": "$60–$90/hour"
  },
  {
    "id": "mercor-5",
    "job_title": "Python Software Engineer",
    "company_name": "Mercor",
    "location": "Remote",
    "job_type": "Hourly Contract",
    "salary_range": "$100/hr",
    "monthly_earnings": "$16,000+/mo",
    "required_skills": ["Python", "FastAPI", "Async/Await", "Testing", "Production Systems"],
    "match_score": 97,
    "skill_overlap": ["Python", "FastAPI", "Testing"],
    "missing_skills": [],
    "hired_count": 29,
    "job_link": "https://t.mercor.com/xPT2C",
    "is_featured": true,
    "pay_label": "$100/hour"
  },
  {
    "id": "mercor-6",
    "job_title": "Software Developer",
    "company_name": "Mercor",
    "location": "Remote (US)",
    "job_type": "Hourly Contract",
    "salary_range": "$70 – $100/hr",
    "monthly_earnings": "$11,200+/mo",
    "required_skills": ["Software Development", "4+ Years Experience", "System Design", "APIs"],
    "match_score": 92,
    "skill_overlap": ["Software Development", "System Design"],
    "missing_skills": ["APIs"],
    "hired_count": 44,
    "job_link": "https://t.mercor.com/ipKFz",
    "is_featured": true,
    "pay_label": "$70–$100/hour"
  }
]
